{"lang": "en", "author_id": "49893262", "possibly_sensitive": false, "created_at": "2014-01-27T04:15:49.000Z", "referenced_tweets": [{"type": "replied_to", "id": "427652211414274048"}], "conversation_id": "427652211414274048", "entities": {"mentions": [{"start": 0, "end": 14, "username": "DRUDGE_REPORT", "id": "14887069"}]}, "in_reply_to_user_id": "14669951", "public_metrics": {"retweet_count": 0, "reply_count": 1, "like_count": 0, "quote_count": 0}, "source": "Twitter for iPhone", "text": "@DRUDGE_REPORT 75% of heavy smokers never contract lung cancer.", "id": "427656164864561152", "reply_settings": "everyone"}