{"source": "Twitter for Android", "id": "536830069050593280", "text": ".@Independent @MPeadon Huh, guess it was only later they became ragingly sexist", "reply_settings": "everyone", "public_metrics": {"retweet_count": 0, "reply_count": 1, "like_count": 0, "quote_count": 0}, "created_at": "2014-11-24T10:33:56.000Z", "entities": {"mentions": [{"start": 1, "end": 13, "username": "Independent", "id": "16973333"}, {"start": 14, "end": 22, "username": "MPeadon", "id": "1020993247"}]}, "possibly_sensitive": false, "lang": "en", "author_id": "156198682", "in_reply_to_user_id": "16973333", "referenced_tweets": [{"type": "replied_to", "id": "536827853669941248"}], "conversation_id": "536827853669941248"}