{"public_metrics": {"retweet_count": 0, "reply_count": 0, "like_count": 1, "quote_count": 0}, "entities": {"mentions": [{"start": 0, "end": 10, "username": "JuddLegum", "id": "15464697"}, {"start": 11, "end": 24, "username": "RiskyLiberal", "id": "869049313"}], "hashtags": [{"start": 78, "end": 90, "tag": "coronavirus"}]}, "in_reply_to_user_id": "15464697", "text": "@JuddLegum @RiskyLiberal I'm sure a wall at the southern border will stop the #coronavirus form entering through the airports... /s", "reply_settings": "everyone", "created_at": "2020-02-26T06:30:32.000Z", "source": "Twitter Web App", "context_annotations": [{"domain": {"id": "10", "name": "Person", "description": "Named people in the world like Nelson Mandela"}, "entity": {"id": "1054453013526413312", "name": "Judd Legum", "description": "Judd Legum"}}, {"domain": {"id": "94", "name": "Journalist", "description": "A journalist like 'Anderson Cooper'"}, "entity": {"id": "1054453013526413312", "name": "Judd Legum", "description": "Judd Legum"}}, {"domain": {"id": "123", "name": "Ongoing News Story", "description": "Ongoing News Stories like 'Brexit'"}, "entity": {"id": "1220701888179359745", "name": "COVID-19"}}], "author_id": "261743416", "referenced_tweets": [{"type": "replied_to", "id": "1232452547178196992"}], "id": "1232553514385018881", "lang": "en", "possibly_sensitive": false, "conversation_id": "1232452547178196992"}