{"text": "@realDonaldTrump I'll buy you all free hotdogs if you have one in Wuhan.", "id": "1233417900351946754", "context_annotations": [{"domain": {"id": "10", "name": "Person", "description": "Named people in the world like Nelson Mandela"}, "entity": {"id": "799022225751871488", "name": "Donald Trump", "description": "US President Donald Trump"}}, {"domain": {"id": "35", "name": "Politician", "description": "Politicians in the world, like Joe Biden"}, "entity": {"id": "799022225751871488", "name": "Donald Trump", "description": "US President Donald Trump"}}, {"domain": {"id": "30", "name": "Entities [Entity Service]", "description": "Entity Service top level domain, every item that is in Entity Service should be in this domain"}, "entity": {"id": "825047692124442624", "name": "Food", "description": "Food"}}, {"domain": {"id": "30", "name": "Entities [Entity Service]", "description": "Entity Service top level domain, every item that is in Entity Service should be in this domain"}, "entity": {"id": "824777229892661248", "name": "Generic Food", "description": "Generic Food"}}, {"domain": {"id": "30", "name": "Entities [Entity Service]", "description": "Entity Service top level domain, every item that is in Entity Service should be in this domain"}, "entity": {"id": "842071370108293120", "name": "Hot dogs", "description": "Hot dog"}}], "reply_settings": "everyone", "conversation_id": "1233403109038346246", "entities": {"mentions": [{"start": 0, "end": 16, "username": "realDonaldTrump", "id": "25073877"}], "annotations": [{"start": 66, "end": 70, "probability": 0.689, "type": "Place", "normalized_text": "Wuhan"}]}, "public_metrics": {"retweet_count": 0, "reply_count": 0, "like_count": 3, "quote_count": 0}, "author_id": "37704788", "source": "Twitter Web App", "referenced_tweets": [{"type": "replied_to", "id": "1233403109038346246"}], "possibly_sensitive": false, "lang": "en", "created_at": "2020-02-28T15:45:17.000Z", "in_reply_to_user_id": "25073877"}