{"created_at": "2020-03-25T17:03:19.000Z", "source": "Twitter Web App", "public_metrics": {"retweet_count": 0, "reply_count": 0, "like_count": 0, "quote_count": 0}, "author_id": "1108837649140322317", "reply_settings": "everyone", "text": "@Alyssa_Milano @detroit_rachel Great idea, but can we be sure they are clean enough to deal with sick people. The last thing we need is black mold &amp; foodborne illness ontop of COVID-19", "in_reply_to_user_id": "26642006", "conversation_id": "1242851039725813761", "lang": "en", "context_annotations": [{"domain": {"id": "10", "name": "Person", "description": "Named people in the world like Nelson Mandela"}, "entity": {"id": "919892167023255552", "name": "Alyssa Milano", "description": "Alyssa Milano"}}, {"domain": {"id": "56", "name": "Actor", "description": "An actor or actress in the world, like Kate Winslet or Leonardo DiCaprio"}, "entity": {"id": "919892167023255552", "name": "Alyssa Milano", "description": "Alyssa Milano"}}, {"domain": {"id": "123", "name": "Ongoing News Story", "description": "Ongoing News Stories like 'Brexit'"}, "entity": {"id": "1220701888179359745", "name": "COVID-19"}}, {"domain": {"id": "29", "name": "Events [Entity Service]", "description": "Entity Service related Events domain"}, "entity": {"id": "1242311410245222400", "name": "Updates on COVID-19 in Australia", "description": "This page is a timeline of Tweets with information and advice from the prime minister, state and federal governments, health authorities and other trusted sources from around Australia. For more, visit https://www.health.gov.au/."}}], "referenced_tweets": [{"type": "replied_to", "id": "1242851039725813761"}], "possibly_sensitive": false, "id": "1242859621775290371", "entities": {"mentions": [{"start": 0, "end": 14, "username": "Alyssa_Milano", "id": "26642006"}, {"start": 15, "end": 30, "username": "detroit_rachel", "id": "4552846169"}]}}