{"entities": {"mentions": [{"start": 34, "end": 44, "username": "Bkcharlie", "id": "22486517"}]}, "referenced_tweets": [{"type": "replied_to", "id": "1245521453002493952"}], "context_annotations": [{"domain": {"id": "123", "name": "Ongoing News Story", "description": "Ongoing News Stories like 'Brexit'"}, "entity": {"id": "1220701888179359745", "name": "COVID-19"}}, {"domain": {"id": "29", "name": "Events [Entity Service]", "description": "Entity Service related Events domain"}, "entity": {"id": "1219057585707315201", "name": "COVID-19: Latest news updates from around the world", "description": "This page is a timeline of Tweets with the latest information and updates on COVID-19 from experts, journalists, health authorities and other trusted sources from around the world. For more on COVID-19, visit: twitter.com/explore/tabs/covid-19"}}], "public_metrics": {"retweet_count": 0, "reply_count": 1, "like_count": 1, "quote_count": 0}, "in_reply_to_user_id": "901955736519016448", "lang": "en", "conversation_id": "1245521453002493952", "created_at": "2020-04-02T17:34:06.000Z", "text": "@CathiBrennan67 The key is buried @Bkcharlie's link.\nHopkins' worst case estimated mortality rate for flu is 0.06%. For COVID19 based on current data it's 5%. \nOr, your risk of mortality from getting COVID19 ONCE is equal to the total risk from getting the flu every year for 83 straight years.", "reply_settings": "everyone", "author_id": "14680410", "source": "Twitter Web App", "possibly_sensitive": false, "id": "1245766471512449024"}