{"in_reply_to_user_id": "355989081", "possibly_sensitive": false, "referenced_tweets": [{"type": "replied_to", "id": "1250794754490732550"}], "lang": "en", "entities": {"annotations": [{"start": 37, "end": 47, "probability": 0.631, "type": "Place", "normalized_text": "Middle East"}], "mentions": [{"start": 0, "end": 4, "username": "ANI", "id": "355989081"}, {"start": 83, "end": 96, "username": "CMOTamilnadu", "id": "844890761409777664"}, {"start": 158, "end": 167, "username": "AmitShah", "id": "1447949844"}], "hashtags": [{"start": 61, "end": 76, "tag": "TablighiJamaat"}, {"start": 134, "end": 142, "tag": "COVID19"}]}, "id": "1250797431748345857", "reply_settings": "everyone", "source": "Twitter Web App", "author_id": "1693278649", "public_metrics": {"retweet_count": 0, "reply_count": 0, "like_count": 0, "quote_count": 0}, "text": "@ANI Really? What about Workers from Middle East? What about #TablighiJamaat ? But @CMOTamilNadu only holds Only rich responsible for #COVID19 ! What is this @AmitShah ji ?", "conversation_id": "1250794754490732550", "created_at": "2020-04-16T14:45:21.000Z", "context_annotations": [{"domain": {"id": "10", "name": "Person", "description": "Named people in the world like Nelson Mandela"}, "entity": {"id": "1111315542407667712", "name": "Amit Shah", "description": "Amit Shah"}}, {"domain": {"id": "35", "name": "Politician", "description": "Politicians in the world, like Joe Biden"}, "entity": {"id": "1111315542407667712", "name": "Amit Shah", "description": "Amit Shah"}}, {"domain": {"id": "45", "name": "Brand Vertical", "description": "Top level entities that describe a Brands industry"}, "entity": {"id": "781974597310615553", "name": "Entertainment"}}, {"domain": {"id": "46", "name": "Brand Category", "description": "Categories within Brand Verticals that narrow down the scope of Brands"}, "entity": {"id": "781974597105094656", "name": "TV/Movies Related"}}, {"domain": {"id": "47", "name": "Brand", "description": "Brands and Companies"}, "entity": {"id": "1138061572880777217", "name": "ANI (Asian News International)"}}, {"domain": {"id": "123", "name": "Ongoing News Story", "description": "Ongoing News Stories like 'Brexit'"}, "entity": {"id": "1220701888179359745", "name": "COVID-19"}}]}