{"reply_settings": "everyone", "conversation_id": "1250813696818937857", "text": "@Javedakhtarjadu Mr. Pappu Akhtar Ji What about the mortality rate in Maharashtra due to Covid19 which is one of the highest in world ? You guys are badly exposing yourself these days.\n\nhttps://t.co/SwJQXgmJqj", "in_reply_to_user_id": "122995784", "lang": "en", "entities": {"urls": [{"start": 186, "end": 209, "url": "https://t.co/SwJQXgmJqj", "expanded_url": "https://www.google.com/amp/s/m.timesofindia.com/india/maharashtra-covid-19-mortality-rate-highest-in-the-world/amp_articleshow/75143435.cms", "display_url": "google.com/amp/s/m.timeso\u2026"}], "annotations": [{"start": 17, "end": 35, "probability": 0.6755, "type": "Person", "normalized_text": "Mr. Pappu Akhtar Ji"}, {"start": 70, "end": 80, "probability": 0.962, "type": "Place", "normalized_text": "Maharashtra"}, {"start": 89, "end": 95, "probability": 0.4965, "type": "Place", "normalized_text": "Covid19"}], "mentions": [{"start": 0, "end": 16, "username": "Javedakhtarjadu", "id": "122995784"}]}, "author_id": "243096334", "context_annotations": [{"domain": {"id": "123", "name": "Ongoing News Story", "description": "Ongoing News Stories like 'Brexit'"}, "entity": {"id": "1220701888179359745", "name": "COVID-19"}}, {"domain": {"id": "29", "name": "Events [Entity Service]", "description": "Entity Service related Events domain"}, "entity": {"id": "1219057585707315201", "name": "COVID-19: Latest news updates from around the world", "description": "This page is a timeline of Tweets with the latest information and updates on COVID-19 from experts, journalists, health authorities and other trusted sources from around the world. For more on COVID-19, visit: twitter.com/explore/tabs/covid-19"}}], "public_metrics": {"retweet_count": 20, "reply_count": 5, "like_count": 59, "quote_count": 1}, "referenced_tweets": [{"type": "replied_to", "id": "1250813696818937857"}], "possibly_sensitive": false, "id": "1250822244386746370", "created_at": "2020-04-16T16:23:56.000Z", "source": "Twitter for Android"}