{"public_metrics": {"retweet_count": 0, "reply_count": 0, "like_count": 5, "quote_count": 0}, "source": "Twitter Web App", "possibly_sensitive": false, "entities": {"mentions": [{"start": 0, "end": 8, "username": "SkyNews", "id": "7587032"}]}, "created_at": "2020-04-22T12:28:49.000Z", "id": "1252937402991161345", "text": "@SkyNews Born 26th May 1949. Today is 22nd April 2020 hence he is at least 70 and should be isolating! Knowing him he'd probably invite coronavirus to tea! How he can show his face after that humiliation in December!", "lang": "en", "in_reply_to_user_id": "7587032", "reply_settings": "everyone", "referenced_tweets": [{"type": "replied_to", "id": "1252936001313558528"}], "author_id": "345018436", "conversation_id": "1252936001313558528", "context_annotations": [{"domain": {"id": "47", "name": "Brand", "description": "Brands and Companies"}, "entity": {"id": "1100765157339234304", "name": "Sky News", "description": "Sky News"}}, {"domain": {"id": "123", "name": "Ongoing News Story", "description": "Ongoing News Stories like 'Brexit'"}, "entity": {"id": "1220701888179359745", "name": "COVID-19"}}]}