{"lang": "en", "created_at": "2020-04-20T00:26:42.000Z", "source": "Twitter for iPhone", "reply_settings": "everyone", "text": "@RichardDawkins No! HK people did not follow WHO guidelines, stop whitewash WHO! #FakeNews #TaiwanCanHelp #WuhanVirus", "public_metrics": {"retweet_count": 0, "reply_count": 0, "like_count": 0, "quote_count": 0}, "entities": {"mentions": [{"start": 0, "end": 15, "username": "RichardDawkins", "id": "15143478"}], "hashtags": [{"start": 81, "end": 90, "tag": "FakeNews"}, {"start": 91, "end": 105, "tag": "TaiwanCanHelp"}, {"start": 106, "end": 117, "tag": "WuhanVirus"}]}, "referenced_tweets": [{"type": "replied_to", "id": "1251418534640402433"}], "context_annotations": [{"domain": {"id": "123", "name": "Ongoing News Story", "description": "Ongoing News Stories like 'Brexit'"}, "entity": {"id": "1220701888179359745", "name": "COVID-19"}}, {"domain": {"id": "29", "name": "Events [Entity Service]", "description": "Entity Service related Events domain"}, "entity": {"id": "1219057585707315201", "name": "COVID-19: Latest news updates from around the world", "description": "This page is a timeline of Tweets with the latest information and updates on COVID-19 from experts, journalists, health authorities and other trusted sources from around the world. For more on COVID-19, visit: twitter.com/explore/tabs/covid-19"}}], "conversation_id": "1251418534640402433", "author_id": "1208722199810658304", "possibly_sensitive": false, "id": "1252030897437712387", "in_reply_to_user_id": "15143478"}