{"text": "@realDonaldTrump .@SmithfieldFoods' South Dakota Plant Revealed to Be One of America's Biggest COVID-19 Clusters.\n&gt;800 workers of the South Dakota plant have been infected (Updated) &amp; They Are Blaming the Workers!\nReally?\nDeregulation Endangers Everyone!\n#GOPFailedAmerica\nhttps://t.co/fDuYYVHW5t", "entities": {"urls": [{"start": 280, "end": 303, "url": "https://t.co/fDuYYVHW5t", "expanded_url": "https://people.com/health/smithfield-foods-plant-one-of-america-biggest-covid-19-clusters/", "display_url": "people.com/health/smithfi\u2026"}], "mentions": [{"start": 0, "end": 16, "username": "realDonaldTrump", "id": "25073877"}, {"start": 18, "end": 34, "username": "SmithfieldFoods", "id": "57116047"}], "hashtags": [{"start": 262, "end": 279, "tag": "GOPFailedAmerica"}], "annotations": [{"start": 36, "end": 47, "probability": 0.6252, "type": "Place", "normalized_text": "South Dakota"}, {"start": 77, "end": 83, "probability": 0.9788, "type": "Place", "normalized_text": "America"}, {"start": 134, "end": 145, "probability": 0.869, "type": "Place", "normalized_text": "South Dakota"}]}, "id": "1253011713642938369", "context_annotations": [{"domain": {"id": "10", "name": "Person", "description": "Named people in the world like Nelson Mandela"}, "entity": {"id": "799022225751871488", "name": "Donald Trump", "description": "US President Donald Trump"}}, {"domain": {"id": "35", "name": "Politician", "description": "Politicians in the world, like Joe Biden"}, "entity": {"id": "799022225751871488", "name": "Donald Trump", "description": "US President Donald Trump"}}, {"domain": {"id": "123", "name": "Ongoing News Story", "description": "Ongoing News Stories like 'Brexit'"}, "entity": {"id": "1220701888179359745", "name": "COVID-19"}}], "reply_settings": "everyone", "conversation_id": "1252928613743235072", "public_metrics": {"retweet_count": 0, "reply_count": 0, "like_count": 0, "quote_count": 0}, "author_id": "165071554", "source": "Twitter for Android", "referenced_tweets": [{"type": "replied_to", "id": "1252928613743235072"}], "possibly_sensitive": false, "lang": "en", "created_at": "2020-04-22T17:24:07.000Z", "in_reply_to_user_id": "25073877"}