{"context_annotations": [{"domain": {"id": "123", "name": "Ongoing News Story", "description": "Ongoing News Stories like 'Brexit'"}, "entity": {"id": "1220701888179359745", "name": "COVID-19"}}, {"domain": {"id": "10", "name": "Person", "description": "Named people in the world like Nelson Mandela"}, "entity": {"id": "10040395078", "name": "Joe Biden", "description": "US President Joe Biden"}}, {"domain": {"id": "10", "name": "Person", "description": "Named people in the world like Nelson Mandela"}, "entity": {"id": "884781076484202496", "name": "Donald Trump Jr.", "description": "Donald Trump Jr."}}, {"domain": {"id": "35", "name": "Politician", "description": "Politicians in the world, like Joe Biden"}, "entity": {"id": "10040395078", "name": "Joe Biden", "description": "US President Joe Biden"}}, {"domain": {"id": "29", "name": "Events [Entity Service]", "description": "Entity Service related Events domain"}, "entity": {"id": "1219057585707315201", "name": "COVID-19: Latest news updates from around the world", "description": "This page is a timeline of Tweets with the latest information and updates on COVID-19 from experts, journalists, health authorities and other trusted sources from around the world. For more on COVID-19, visit: twitter.com/explore/tabs/covid-19"}}], "conversation_id": "1260740872620183552", "created_at": "2020-05-14T01:17:02.000Z", "author_id": "39344374", "possibly_sensitive": false, "source": "Twitter for iPhone", "reply_settings": "everyone", "public_metrics": {"retweet_count": 8711, "reply_count": 1894, "like_count": 33523, "quote_count": 531}, "text": "Joe Biden choosing to defend China on the day they are credibly accused of trying to hack the companies that are trying to come up with a cure for the coronavirus, that they started and enabled to spread, is a new low even for someone who\u2019s been bought and paid for by China!", "id": "1260740872620183552", "lang": "en", "entities": {"annotations": [{"start": 0, "end": 8, "probability": 0.9971, "type": "Person", "normalized_text": "Joe Biden"}, {"start": 29, "end": 33, "probability": 0.9869, "type": "Place", "normalized_text": "China"}, {"start": 269, "end": 273, "probability": 0.9493, "type": "Place", "normalized_text": "China"}]}}