{"context_annotations": [{"domain": {"id": "123", "name": "Ongoing News Story", "description": "Ongoing News Stories like 'Brexit'"}, "entity": {"id": "1220701888179359745", "name": "COVID-19"}}], "author_id": "4434241098", "entities": {"mentions": [{"start": 0, "end": 11, "username": "SiegelAtty", "id": "2440065786"}]}, "referenced_tweets": [{"type": "replied_to", "id": "1261863690346868736"}], "id": "1262136325534126082", "lang": "en", "in_reply_to_user_id": "2440065786", "text": "@SiegelAtty Suggest that this guy read and follow some real news and educate himself about how lethal the coronavirus is and how easily transmissible it is. \nHe\u2019s a disgrace to the human species.", "public_metrics": {"retweet_count": 0, "reply_count": 0, "like_count": 1, "quote_count": 0}, "conversation_id": "1261863690346868736", "created_at": "2020-05-17T21:42:04.000Z", "source": "Twitter for iPhone", "reply_settings": "everyone", "possibly_sensitive": false}