{"conversation_id": "1264329603939696640", "possibly_sensitive": false, "entities": {"urls": [{"start": 240, "end": 263, "url": "https://t.co/oDklKl8c4d", "expanded_url": "https://twitter.com/Parise_Shankuan/status/1264390861791485952/photo/1", "display_url": "pic.twitter.com/oDklKl8c4d"}, {"start": 240, "end": 263, "url": "https://t.co/oDklKl8c4d", "expanded_url": "https://twitter.com/Parise_Shankuan/status/1264390861791485952/photo/1", "display_url": "pic.twitter.com/oDklKl8c4d"}, {"start": 240, "end": 263, "url": "https://t.co/oDklKl8c4d", "expanded_url": "https://twitter.com/Parise_Shankuan/status/1264390861791485952/photo/1", "display_url": "pic.twitter.com/oDklKl8c4d"}, {"start": 240, "end": 263, "url": "https://t.co/oDklKl8c4d", "expanded_url": "https://twitter.com/Parise_Shankuan/status/1264390861791485952/photo/1", "display_url": "pic.twitter.com/oDklKl8c4d"}], "annotations": [{"start": 62, "end": 66, "probability": 0.777, "type": "Place", "normalized_text": "China"}], "mentions": [{"start": 0, "end": 16, "username": "realDonaldTrump", "id": "25073877"}]}, "reply_settings": "everyone", "author_id": "772822854", "source": "Twitter Web App", "created_at": "2020-05-24T03:00:47.000Z", "in_reply_to_user_id": "25073877", "referenced_tweets": [{"type": "replied_to", "id": "1264329603939696640"}], "context_annotations": [{"domain": {"id": "10", "name": "Person", "description": "Named people in the world like Nelson Mandela"}, "entity": {"id": "799022225751871488", "name": "Donald Trump", "description": "US President Donald Trump"}}, {"domain": {"id": "35", "name": "Politician", "description": "Politicians in the world, like Joe Biden"}, "entity": {"id": "799022225751871488", "name": "Donald Trump", "description": "US President Donald Trump"}}, {"domain": {"id": "123", "name": "Ongoing News Story", "description": "Ongoing News Stories like 'Brexit'"}, "entity": {"id": "1220701888179359745", "name": "COVID-19"}}, {"domain": {"id": "29", "name": "Events [Entity Service]", "description": "Entity Service related Events domain"}, "entity": {"id": "1219057585707315201", "name": "COVID-19: Latest news updates from around the world", "description": "This page is a timeline of Tweets with the latest information and updates on COVID-19 from experts, journalists, health authorities and other trusted sources from around the world. For more on COVID-19, visit: twitter.com/explore/tabs/covid-19"}}], "public_metrics": {"retweet_count": 0, "reply_count": 0, "like_count": 0, "quote_count": 0}, "id": "1264390861791485952", "lang": "en", "attachments": {"media_keys": ["3_1264390852001988609", "3_1264390852010340353", "3_1264390852035534848", "3_1264390852010369027"]}, "text": "@realDonaldTrump or sell: COVID-19 IgG/IgM Rapit Test Kit\n\nIn China white list and ANVISA list, \nTUV test report, CE approval\nthe total conformity rate is 99%.\nWe are Personal Protect Equipment Carrier\n\nIf you are interested, please PM us. https://t.co/oDklKl8c4d"}