{"public_metrics": {"retweet_count": 0, "reply_count": 0, "like_count": 0, "quote_count": 0}, "reply_settings": "everyone", "id": "1266884666306580480", "conversation_id": "1266762499627638785", "source": "Twitter for iPhone", "possibly_sensitive": false, "in_reply_to_user_id": "1201670995435646976", "context_annotations": [{"domain": {"id": "123", "name": "Ongoing News Story", "description": "Ongoing News Stories like 'Brexit'"}, "entity": {"id": "1220701888179359745", "name": "COVID-19"}}], "text": "@laurenboebert CoronaVirus is over. It didn\u2019t work for the democrats. These riots are why there will be no more social distancing and masks forced upon us. Thousands of protesters are spreading anything and everything everywhere. If it was even an issue. #CoronaVirusSpikesAfterProtests", "entities": {"hashtags": [{"start": 255, "end": 286, "tag": "CoronaVirusSpikesAfterProtests"}], "mentions": [{"start": 0, "end": 14, "username": "laurenboebert", "id": "1201670995435646976"}]}, "referenced_tweets": [{"type": "replied_to", "id": "1266762499627638785"}], "lang": "en", "created_at": "2020-05-31T00:10:16.000Z", "author_id": "2777102431"}