{"conversation_id": "1269038270064844801", "text": "@RepMaxineWaters @GavinNewsom is the dictator !     He\u2019s not giving stats on #BlackLivesMatter that #COVID19 affects the Black population worse than others!  Where are @GavinNewsom s Charts &amp; Graphs ?Sharing the Facts of @CDCgov findings you are using your own!  Denying the truth! @greggutfeld", "in_reply_to_user_id": "36686040", "author_id": "774025055818903552", "entities": {"mentions": [{"start": 0, "end": 16, "username": "RepMaxineWaters", "id": "36686040"}, {"start": 17, "end": 29, "username": "GavinNewsom", "id": "11347122"}, {"start": 168, "end": 180, "username": "GavinNewsom", "id": "11347122"}, {"start": 225, "end": 232, "username": "CDCgov", "id": "146569971"}, {"start": 286, "end": 298, "username": "greggutfeld", "id": "28628850"}], "hashtags": [{"start": 77, "end": 94, "tag": "BlackLivesMatter"}, {"start": 100, "end": 108, "tag": "COVID19"}]}, "context_annotations": [{"domain": {"id": "10", "name": "Person", "description": "Named people in the world like Nelson Mandela"}, "entity": {"id": "964532337168953344", "name": "Maxine Waters", "description": "US Representative Maxine Waters (CA-43)"}}, {"domain": {"id": "10", "name": "Person", "description": "Named people in the world like Nelson Mandela"}, "entity": {"id": "999344319885524992", "name": "Gavin Newsom", "description": "Candidate for Governor of California Gavin Newsom"}}, {"domain": {"id": "35", "name": "Politician", "description": "Politicians in the world, like Joe Biden"}, "entity": {"id": "964532337168953344", "name": "Maxine Waters", "description": "US Representative Maxine Waters (CA-43)"}}, {"domain": {"id": "35", "name": "Politician", "description": "Politicians in the world, like Joe Biden"}, "entity": {"id": "999344319885524992", "name": "Gavin Newsom", "description": "Candidate for Governor of California Gavin Newsom"}}, {"domain": {"id": "123", "name": "Ongoing News Story", "description": "Ongoing News Stories like 'Brexit'"}, "entity": {"id": "1220701888179359745", "name": "COVID-19"}}], "possibly_sensitive": false, "reply_settings": "everyone", "lang": "en", "source": "Twitter for iPhone", "public_metrics": {"retweet_count": 0, "reply_count": 1, "like_count": 0, "quote_count": 0}, "id": "1269494858097418240", "referenced_tweets": [{"type": "replied_to", "id": "1269038270064844801"}], "created_at": "2020-06-07T05:02:14.000Z"}