{"conversation_id": "1253219375982747648", "possibly_sensitive": false, "entities": {"urls": [{"start": 260, "end": 283, "url": "https://t.co/nf1biY5lzT", "expanded_url": "https://www.optimumiq.net/coronavirus-covid-19.html", "display_url": "optimumiq.net/coronavirus-co\u2026"}], "mentions": [{"start": 0, "end": 12, "username": "georgesoros", "id": "23125257"}]}, "reply_settings": "everyone", "author_id": "198776276", "source": "Twitter Web App", "created_at": "2020-06-17T08:25:30.000Z", "in_reply_to_user_id": "23125257", "referenced_tweets": [{"type": "replied_to", "id": "1253219375982747648"}], "context_annotations": [{"domain": {"id": "10", "name": "Person", "description": "Named people in the world like Nelson Mandela"}, "entity": {"id": "1018889957123821569", "name": "George Soros", "description": "George Soros"}}], "public_metrics": {"retweet_count": 0, "reply_count": 0, "like_count": 0, "quote_count": 0}, "id": "1273169888207687682", "lang": "en", "text": "@georgesoros Right here, your goal is to access 1 Trillion for yourself. You are not thinking about mankind. Greed - I guess you have been so empty and so numb in your life for so long, you can't even grasp the death that's been undertaking your entire being. https://t.co/nf1biY5lzT"}