{"entities": {"annotations": [{"start": 216, "end": 220, "probability": 0.9589, "type": "Person", "normalized_text": "Soros"}, {"start": 236, "end": 238, "probability": 0.6459, "type": "Person", "normalized_text": "DJT"}], "mentions": [{"start": 0, "end": 13, "username": "RudyGiuliani", "id": "770781940341288960"}]}, "id": "1274146216205582336", "context_annotations": [{"domain": {"id": "123", "name": "Ongoing News Story", "description": "Ongoing News Stories like 'Brexit'"}, "entity": {"id": "1220701888179359745", "name": "COVID-19"}}, {"domain": {"id": "29", "name": "Events [Entity Service]", "description": "Entity Service related Events domain"}, "entity": {"id": "1219057585707315201", "name": "COVID-19: Latest news updates from around the world", "description": "This page is a timeline of Tweets with the latest information and updates on COVID-19 from experts, journalists, health authorities and other trusted sources from around the world. For more on COVID-19, visit: twitter.com/explore/tabs/covid-19"}}], "referenced_tweets": [{"type": "replied_to", "id": "1274140035881799687"}], "lang": "en", "reply_settings": "everyone", "possibly_sensitive": false, "public_metrics": {"retweet_count": 0, "reply_count": 0, "like_count": 0, "quote_count": 0}, "text": "@RudyGiuliani Investigations re COVID19 need 2 follow big donors $ &amp; c if Chinese ppl who came over &amp; spread it here &amp; WWide (deflect), didnt get big $ deposit in acct somewhere? Know it sounds like conspiracy; BUT, Soros &amp; OTHERS HATE DJT THAT MUCH!!!! It is ELECTION YR?", "conversation_id": "1274140035881799687", "source": "Twitter for Android", "created_at": "2020-06-20T01:05:05.000Z", "in_reply_to_user_id": "770781940341288960", "author_id": "848368359490105344"}