{"reply_settings": "everyone", "id": "1274457730732797952", "entities": {"mentions": [{"start": 0, "end": 13, "username": "AsteadWesley", "id": "362111287"}]}, "public_metrics": {"retweet_count": 0, "reply_count": 0, "like_count": 0, "quote_count": 0}, "in_reply_to_user_id": "362111287", "source": "Twitter for iPhone", "text": "@AsteadWesley Can someone edit this to show the coronavirus running wild?", "conversation_id": "1274440553061588992", "lang": "en", "referenced_tweets": [{"type": "replied_to", "id": "1274440553061588992"}], "created_at": "2020-06-20T21:42:55.000Z", "context_annotations": [{"domain": {"id": "3", "name": "TV Shows", "description": "Television shows from around the world"}, "entity": {"id": "10032318878", "name": "Running Wild With Bear Grylls"}}, {"domain": {"id": "123", "name": "Ongoing News Story", "description": "Ongoing News Stories like 'Brexit'"}, "entity": {"id": "1220701888179359745", "name": "COVID-19"}}], "author_id": "822129482328719360", "possibly_sensitive": false}