{"lang": "en", "author_id": "29734681", "possibly_sensitive": false, "context_annotations": [{"domain": {"id": "10", "name": "Person", "description": "Named people in the world like Nelson Mandela"}, "entity": {"id": "799022225751871488", "name": "Donald Trump", "description": "US President Donald Trump"}}, {"domain": {"id": "35", "name": "Politician", "description": "Politicians in the world, like Joe Biden"}, "entity": {"id": "799022225751871488", "name": "Donald Trump", "description": "US President Donald Trump"}}, {"domain": {"id": "123", "name": "Ongoing News Story", "description": "Ongoing News Stories like 'Brexit'"}, "entity": {"id": "1220701888179359745", "name": "COVID-19"}}], "created_at": "2020-06-29T13:06:07.000Z", "referenced_tweets": [{"type": "replied_to", "id": "1277568447841517570"}], "conversation_id": "1277568447841517570", "entities": {"hashtags": [{"start": 46, "end": 54, "tag": "testing"}, {"start": 135, "end": 155, "tag": "incrediblestupidity"}], "mentions": [{"start": 0, "end": 15, "username": "ProjectLincoln", "id": "1205226529455632385"}, {"start": 115, "end": 131, "username": "realDonaldTrump", "id": "25073877"}]}, "in_reply_to_user_id": "1205226529455632385", "public_metrics": {"retweet_count": 0, "reply_count": 0, "like_count": 0, "quote_count": 0}, "source": "Twitter for iPhone", "text": "@ProjectLincoln That\u2019s the result of too much #testing... otherwise COVID-19 would\u2019ve disappeared already... right @realDonaldTrump? \ud83d\ude33 #incrediblestupidity", "id": "1277589162904952832", "reply_settings": "everyone"}