{"in_reply_to_user_id": "15891430", "lang": "en", "conversation_id": "1278507266145124352", "entities": {"mentions": [{"start": 0, "end": 11, "username": "jodikantor", "id": "15891430"}, {"start": 12, "end": 21, "username": "NPRKelly", "id": "564069706"}]}, "context_annotations": [{"domain": {"id": "10", "name": "Person", "description": "Named people in the world like Nelson Mandela"}, "entity": {"id": "1070710942692831232", "name": "Jodi Kantor", "description": "American journalist"}}, {"domain": {"id": "94", "name": "Journalist", "description": "A journalist like 'Anderson Cooper'"}, "entity": {"id": "1070710942692831232", "name": "Jodi Kantor", "description": "American journalist"}}, {"domain": {"id": "123", "name": "Ongoing News Story", "description": "Ongoing News Stories like 'Brexit'"}, "entity": {"id": "1220701888179359745", "name": "COVID-19"}}, {"domain": {"id": "29", "name": "Events [Entity Service]", "description": "Entity Service related Events domain"}, "entity": {"id": "1219057585707315201", "name": "COVID-19: Latest news updates from around the world", "description": "This page is a timeline of Tweets with the latest information and updates on COVID-19 from experts, journalists, health authorities and other trusted sources from around the world. For more on COVID-19, visit: twitter.com/explore/tabs/covid-19"}}], "reply_settings": "everyone", "public_metrics": {"retweet_count": 0, "reply_count": 0, "like_count": 1, "quote_count": 0}, "source": "TweetDeck", "id": "1278695119173148672", "referenced_tweets": [{"type": "replied_to", "id": "1278507266145124352"}], "text": "@jodikantor @NPRKelly Lets pack thousands of little petri dishes (kids) that NEVER touch their faces onto buses, into classrooms, hallways, playgrounds, and lunchrooms.\nYou think a bar spread COVID-19 fast?\nReopening schools is going to be an unmitigated disaster.", "author_id": "839066888", "possibly_sensitive": false, "created_at": "2020-07-02T14:20:48.000Z"}