{"in_reply_to_user_id": "25073877", "possibly_sensitive": false, "referenced_tweets": [{"type": "replied_to", "id": "1278715220677013504"}], "entities": {"urls": [{"start": 122, "end": 145, "url": "https://t.co/ht8yblFG4d", "expanded_url": "https://www.cnbc.com/amp/2020/07/01/official-us-coronavirus-death-toll-is-a-substantial-undercount-of-actual-tally-new-yale-study-finds.html", "display_url": "cnbc.com/amp/2020/07/01\u2026", "images": [{"url": "https://pbs.twimg.com/news_img/1481641280706781184/2ifdEjpL?format=jpg&name=orig", "width": 3000, "height": 2000}, {"url": "https://pbs.twimg.com/news_img/1481641280706781184/2ifdEjpL?format=jpg&name=150x150", "width": 150, "height": 150}], "status": 200, "title": "Official U.S. coronavirus death toll is 'a substantial undercount' of actual tally, Yale study finds", "description": "The 781,000 total deaths in the United States in the three months through May 30 were nearly 19% higher than what would normally be expected, the study said.", "unwound_url": "https://www.cnbc.com/amp/2020/07/01/official-us-coronavirus-death-toll-is-a-substantial-undercount-of-actual-tally-new-yale-study-finds.html"}], "mentions": [{"start": 0, "end": 16, "username": "realDonaldTrump", "id": "25073877"}], "hashtags": [{"start": 29, "end": 43, "tag": "TrumpGenocide"}, {"start": 77, "end": 89, "tag": "TrumpIsAPos"}, {"start": 90, "end": 99, "tag": "COVID\u30fc19"}, {"start": 100, "end": 120, "tag": "CoronavirusPandemic"}]}, "lang": "en", "id": "1278763759843119104", "reply_settings": "everyone", "source": "Twitter for Android", "author_id": "1084980649520496642", "public_metrics": {"retweet_count": 0, "reply_count": 0, "like_count": 0, "quote_count": 0}, "text": "@realDonaldTrump No doubt...\n#TrumpGenocide is worse than is being reported.\n#TrumpIsAPos\n#COVID\u30fc19\n#CoronavirusPandemic \nhttps://t.co/ht8yblFG4d", "conversation_id": "1278715220677013504", "created_at": "2020-07-02T18:53:33.000Z", "context_annotations": [{"domain": {"id": "10", "name": "Person", "description": "Named people in the world like Nelson Mandela"}, "entity": {"id": "799022225751871488", "name": "Donald Trump", "description": "US President Donald Trump"}}, {"domain": {"id": "35", "name": "Politician", "description": "Politicians in the world, like Joe Biden"}, "entity": {"id": "799022225751871488", "name": "Donald Trump", "description": "US President Donald Trump"}}, {"domain": {"id": "123", "name": "Ongoing News Story", "description": "Ongoing News Stories like 'Brexit'"}, "entity": {"id": "1220701888179359745", "name": "COVID-19"}}, {"domain": {"id": "29", "name": "Events [Entity Service]", "description": "Entity Service related Events domain"}, "entity": {"id": "1219057585707315201", "name": "COVID-19: Latest news updates from around the world", "description": "This page is a timeline of Tweets with the latest information and updates on COVID-19 from experts, journalists, health authorities and other trusted sources from around the world. For more on COVID-19, visit: twitter.com/explore/tabs/covid-19"}}]}