{"entities": {"annotations": [{"start": 90, "end": 94, "probability": 0.7107, "type": "Place", "normalized_text": "Libya"}], "mentions": [{"start": 0, "end": 13, "username": "HelenClarkNZ", "id": "191849753"}, {"start": 14, "end": 23, "username": "DrTedros", "id": "189868631"}, {"start": 24, "end": 28, "username": "WHO", "id": "14499829"}, {"start": 29, "end": 44, "username": "MaEllenSirleaf", "id": "1019321315126280192"}, {"start": 45, "end": 52, "username": "MFATNZ", "id": "1611641605"}, {"start": 53, "end": 61, "username": "NZUNGVA", "id": "2416068013"}, {"start": 62, "end": 67, "username": "NZUN", "id": "1465549688"}, {"start": 68, "end": 84, "username": "jilliandempster", "id": "267647856"}, {"start": 114, "end": 127, "username": "HelenClarkNZ", "id": "191849753"}, {"start": 268, "end": 272, "username": "WHO", "id": "14499829"}, {"start": 292, "end": 301, "username": "DrTedros", "id": "189868631"}], "hashtags": [{"start": 96, "end": 112, "tag": "Congratulations"}, {"start": 226, "end": 238, "tag": "coronavirus"}, {"start": 245, "end": 253, "tag": "COVID19"}], "urls": [{"start": 303, "end": 326, "url": "https://t.co/D6q8VP53sE", "expanded_url": "https://twitter.com/MFATNZ/status/1281360324126367744/photo/1", "display_url": "pic.twitter.com/D6q8VP53sE"}]}, "attachments": {"media_keys": ["3_1281351999137607680"]}, "text": "@HelenClarkNZ @DrTedros @WHO @MaEllenSirleaf @MFATNZ @NZUNGVA @NZUN @jilliandempster From Libya #Congratulations \n@HelenClarkNZ\n on your appointment as co-chair of the Independent Panel for Pandemic Preparedness and Response, #coronavirus back. #COVID19 announced by \n@WHO\n Director-General \n@DrTedros  https://t.co/D6q8VP53sE", "public_metrics": {"retweet_count": 0, "reply_count": 0, "like_count": 1, "quote_count": 0}, "possibly_sensitive": false, "in_reply_to_user_id": "191849753", "id": "1282735375547604994", "author_id": "1221856187660099588", "referenced_tweets": [{"type": "replied_to", "id": "1281202359029268484"}], "source": "Twitter Web App", "reply_settings": "everyone", "conversation_id": "1281202359029268484", "created_at": "2020-07-13T17:55:20.000Z", "context_annotations": [{"domain": {"id": "123", "name": "Ongoing News Story", "description": "Ongoing News Stories like 'Brexit'"}, "entity": {"id": "1220701888179359745", "name": "COVID-19"}}, {"domain": {"id": "29", "name": "Events [Entity Service]", "description": "Entity Service related Events domain"}, "entity": {"id": "1219057585707315201", "name": "COVID-19: Latest news updates from around the world", "description": "This page is a timeline of Tweets with the latest information and updates on COVID-19 from experts, journalists, health authorities and other trusted sources from around the world. For more on COVID-19, visit: twitter.com/explore/tabs/covid-19"}}], "lang": "en"}