{"text": "@NewDay @drsanjaygupta Suddenly like a miracle all coronavirus rates  will be down to zero", "possibly_sensitive": false, "id": "1283408085705465857", "public_metrics": {"retweet_count": 0, "reply_count": 0, "like_count": 0, "quote_count": 0}, "lang": "en", "in_reply_to_user_id": "1375289149", "entities": {"mentions": [{"start": 0, "end": 7, "username": "NewDay", "id": "1375289149"}, {"start": 8, "end": 22, "username": "drsanjaygupta", "id": "18170896"}]}, "context_annotations": [{"domain": {"id": "123", "name": "Ongoing News Story", "description": "Ongoing News Stories like 'Brexit'"}, "entity": {"id": "1220701888179359745", "name": "COVID-19"}}], "referenced_tweets": [{"type": "replied_to", "id": "1283361570261807105"}], "reply_settings": "everyone", "created_at": "2020-07-15T14:28:26.000Z", "author_id": "338552623", "conversation_id": "1283361570261807105", "source": "Twitter for iPhone"}