{"in_reply_to_user_id": "1171109054", "possibly_sensitive": false, "referenced_tweets": [{"type": "replied_to", "id": "1287726845874626566"}], "entities": {"urls": [{"start": 228, "end": 251, "url": "https://t.co/MmFA8ibJS6", "expanded_url": "https://medium.com/@donnakassin/white-americans-are-now-inexorable-pawns-in-trumps-bigger-power-play-7ff923903f53", "display_url": "medium.com/@donnakassin/w\u2026"}], "annotations": [{"start": 161, "end": 167, "probability": 0.5644, "type": "Place", "normalized_text": "America"}], "mentions": [{"start": 0, "end": 9, "username": "rgoodlaw", "id": "1171109054"}]}, "lang": "en", "id": "1288157448453447682", "reply_settings": "everyone", "source": "Twitter Web App", "author_id": "127764317", "public_metrics": {"retweet_count": 0, "reply_count": 1, "like_count": 0, "quote_count": 0}, "text": "@rgoodlaw The numbers have shown a clear trend: The whiter the state, the lower the number of coronavirus deaths. They are only willing to act now because White America is now nonexempt from the consequences of their behavior.\n\nhttps://t.co/MmFA8ibJS6", "conversation_id": "1287726845874626566", "created_at": "2020-07-28T17:00:43.000Z", "context_annotations": [{"domain": {"id": "123", "name": "Ongoing News Story", "description": "Ongoing News Stories like 'Brexit'"}, "entity": {"id": "1220701888179359745", "name": "COVID-19"}}, {"domain": {"id": "29", "name": "Events [Entity Service]", "description": "Entity Service related Events domain"}, "entity": {"id": "1219057585707315201", "name": "COVID-19: Latest news updates from around the world", "description": "This page is a timeline of Tweets with the latest information and updates on COVID-19 from experts, journalists, health authorities and other trusted sources from around the world. For more on COVID-19, visit: twitter.com/explore/tabs/covid-19"}}]}